ergo/__init__.py
ergo/amqp_invoker.py
ergo/config.py
ergo/context.py
ergo/ergo_cli.py
ergo/ergo_click.py
ergo/ergo_cmd.py
ergo/falcon_http_invoker.py
ergo/flask_http_invoker.py
ergo/function_invocable.py
ergo/http_gateway.py
ergo/http_invoker.py
ergo/invoker.py
ergo/key.py
ergo/message.py
ergo/schematic.py
ergo/scope.py
ergo/topic.py
ergo/types.py
ergo/util.py
ergo/version.py
ergo-0.11.3.dist-info/LICENSE.txt
ergo-0.11.3.dist-info/METADATA
ergo-0.11.3.dist-info/WHEEL
ergo-0.11.3.dist-info/entry_points.txt
ergo-0.11.3.dist-info/top_level.txt
ergo-0.11.3.dist-info/RECORD
