Metadata-Version: 2.1
Name: ergo
Version: 0.11.3
Summary: Simple Microservice Development Framework
Home-page: https://github.com/nautiluslabsco/ergo
Author: Matthew Hansen
Author-email: ergo@mattian.com
License: MIT
Download-URL: https://github.com/nautiluslabsco/ergo/archive/v0.11.3.tar.gz
Keywords: execute,microservice,lambda
Platform: UNKNOWN
Classifier: Development Status :: 3 - Alpha
Classifier: Intended Audience :: Developers
Classifier: Topic :: Software Development :: Build Tools
Classifier: License :: OSI Approved :: MIT License
Classifier: Programming Language :: Python :: 3
Classifier: Programming Language :: Python :: 3.7
Classifier: Programming Language :: Python :: 3.8
Classifier: Programming Language :: Python :: 3.9
Classifier: Programming Language :: Python :: 3.10
Requires-Python: >=3
License-File: LICENSE.txt
Requires-Dist: Click
Requires-Dist: flask
Requires-Dist: falcon
Requires-Dist: ansicolors
Requires-Dist: click-default-group
Requires-Dist: pika
Requires-Dist: pyYaml
Requires-Dist: mypy-extensions
Requires-Dist: aio-pika
Requires-Dist: aiomisc
Requires-Dist: graphviz
Requires-Dist: pydash
Requires-Dist: jsons
Requires-Dist: quart
Requires-Dist: kombu
Requires-Dist: jinja2 (<3.1,>=3.0)
